skatepark/__init__.py
skatepark/artifacts/__init__.py
skatepark/artifacts/error_output.py
skatepark/artifacts/structure_artifact.py
skatepark/artifacts/text_output.py
skatepark/drivers/__init__.py
skatepark/drivers/memory/__init__.py
skatepark/drivers/memory/disk_memory_driver.py
skatepark/drivers/memory/memory_driver.py
skatepark/drivers/prompt/__init__.py
skatepark/drivers/prompt/cohere_prompt_driver.py
skatepark/drivers/prompt/openai_prompt_driver.py
skatepark/drivers/prompt/prompt_driver.py
skatepark/memory/__init__.py
skatepark/memory/buffer_pipeline_memory.py
skatepark/memory/pipeline_memory.py
skatepark/memory/pipeline_run.py
skatepark/memory/summary_pipeline_memory.py
skatepark/rules/__init__.py
skatepark/rules/json.py
skatepark/rules/meta.py
skatepark/rules/rule.py
skatepark/schemas/__init__.py
skatepark/schemas/base_schema.py
skatepark/schemas/drivers/__init__.py
skatepark/schemas/drivers/openai_prompt_driver_schema.py
skatepark/schemas/drivers/prompt_driver_schema.py
skatepark/schemas/memory/__init__.py
skatepark/schemas/memory/buffer_pipeline_memory_schema.py
skatepark/schemas/memory/pipeline_memory_schema.py
skatepark/schemas/memory/pipeline_run_schema.py
skatepark/schemas/memory/summary_pipeline_memory_schema.py
skatepark/schemas/polymorphic_schema.py
skatepark/schemas/rule_schema.py
skatepark/schemas/steps/__init__.py
skatepark/schemas/steps/prompt_step_schema.py
skatepark/schemas/steps/step_schema.py
skatepark/schemas/steps/toolkit_step_schema.py
skatepark/schemas/structures/__init__.py
skatepark/schemas/structures/pipeline_schema.py
skatepark/schemas/structures/structure_schema.py
skatepark/schemas/structures/workflow_schema.py
skatepark/schemas/summarizers/__init__.py
skatepark/schemas/summarizers/prompt_driver_summarizer_schema.py
skatepark/schemas/summarizers/summarizer_schema.py
skatepark/schemas/tokenizers/__init__.py
skatepark/schemas/tokenizers/tiktoken_tokenizer_schema.py
skatepark/steps/__init__.py
skatepark/steps/prompt_step.py
skatepark_lib-0.10.0.dist-info/LICENSE
skatepark_lib-0.10.0.dist-info/METADATA
skatepark_lib-0.10.0.dist-info/WHEEL
skatepark_lib-0.10.0.dist-info/RECORD
